nlpflow/Tokenizer.py
nlpflow/__init__.py
nlpflow/model.py
nlpflow/preprocessing.py
nlpflow/utils/__init__.py
nlpflow/utils/decorators.py
nlpflow/utils/exceptions.py
nlpflow-0.0.4.dist-info/LICENSE
nlpflow-0.0.4.dist-info/METADATA
nlpflow-0.0.4.dist-info/WHEEL
nlpflow-0.0.4.dist-info/top_level.txt
nlpflow-0.0.4.dist-info/RECORD
