Metadata-Version: 2.1
Name: nlpflow
Version: 0.0.4
Summary: A powerful toolkit for automating NLP workflows.
Home-page: https://github.com/GiannopoulosK/nlpflow
Author: Konstantinos Giannopoulos
Author-email: giannopoulosk.data@gmail.com
License: Apache License 2.0
Classifier: Programming Language :: Python :: 3
Classifier: License :: OSI Approved :: Apache Software License
Classifier: Operating System :: OS Independent
Classifier: Development Status :: 2 - Pre-Alpha
Requires-Python: >=3.0
License-File: LICENSE
Requires-Dist: numpy>=1.23.0
Requires-Dist: spacy>=3.0.0
Requires-Dist: scikit-learn>=1.0.0
Requires-Dist: optuna>=4.0.0
